pipackager/__init__.py
pipackager/cli.py
tests/__init__.py
tests/test_pipackager.py
pipackager-0.4.7.dist-info/LICENSE
pipackager-0.4.7.dist-info/METADATA
pipackager-0.4.7.dist-info/WHEEL
pipackager-0.4.7.dist-info/entry_points.txt
pipackager-0.4.7.dist-info/top_level.txt
pipackager-0.4.7.dist-info/RECORD
