Metadata-Version: 2.1
Name: pipackager
Version: 0.4.7
Summary: pipackager is a comprehensive tool designed to manage your PyPI package, simplifying tasks such as cleaning old distributions, building new ones, uploading to PyPI, version incrementing, and more.
Home-page: https://github.com/ruvnet/pipackager
Author: rUv
Author-email: your-email@example.com
License: Apache License 2.0
Classifier: Development Status :: 3 - Alpha
Classifier: Intended Audience :: Developers
Classifier: Topic :: Software Development :: Libraries :: Application Frameworks
Classifier: License :: OSI Approved :: Apache Software License
Classifier: Programming Language :: Python :: 3
Classifier: Programming Language :: Python :: 3.7
Classifier: Programming Language :: Python :: 3.8
Classifier: Programming Language :: Python :: 3.9
Classifier: Programming Language :: Python :: 3.10
License-File: LICENSE
Requires-Dist: twine
Requires-Dist: setuptools
Requires-Dist: wheel
Requires-Dist: flake8
Requires-Dist: black
Requires-Dist: pytest
Requires-Dist: pip-upgrader
